aiosql/__init__.py
aiosql/aiosql.py
aiosql/py.typed
aiosql/queries.py
aiosql/query_loader.py
aiosql/types.py
aiosql/utils.py
aiosql/adapters/__init__.py
aiosql/adapters/ageneric.py
aiosql/adapters/aiosqlite.py
aiosql/adapters/apyformat.py
aiosql/adapters/asyncpg.py
aiosql/adapters/duckdb.py
aiosql/adapters/generic.py
aiosql/adapters/mysql.py
aiosql/adapters/pg8000.py
aiosql/adapters/pyformat.py
aiosql/adapters/sqlite3.py
aiosql-15.0.dist-info/licenses/LICENSE
aiosql-15.0.dist-info/METADATA
aiosql-15.0.dist-info/WHEEL
aiosql-15.0.dist-info/top_level.txt
aiosql-15.0.dist-info/RECORD
