Metadata-Version: 2.4
Name: aiosql
Version: 15.0
Summary: Simple SQL in Python
Author-email: "William Vaughn et al." <vaughnwilld@gmail.com>
License-Expression: BSD-2-Clause
Project-URL: repository, https://github.com/nackjicholson/aiosql
Project-URL: documentation, https://nackjicholson.github.io/aiosql/
Project-URL: issues, https://github.com/nackjicholson/aiosql/issues
Project-URL: package, https://pypi.org/project/aiosql/
Classifier: Programming Language :: Python :: 3
Classifier: Programming Language :: SQL
Classifier: Operating System :: OS Independent
Classifier: Development Status :: 5 - Production/Stable
Classifier: Intended Audience :: Developers
Classifier: Topic :: Database
Classifier: Topic :: Software Development :: Libraries :: Python Modules
Requires-Python: >=3.10
License-File: LICENSE
Provides-Extra: dev
Requires-Dist: pytest; extra == "dev"
Requires-Dist: pytest-asyncio; extra == "dev"
Requires-Dist: coverage; extra == "dev"
Requires-Dist: black; extra == "dev"
Requires-Dist: flake8; extra == "dev"
Requires-Dist: ruff; extra == "dev"
Requires-Dist: mypy<1.19; implementation_name == "pypy" and extra == "dev"
Requires-Dist: mypy; implementation_name != "pypy" and extra == "dev"
Requires-Dist: pyright; extra == "dev"
Requires-Dist: types-setuptools; extra == "dev"
Provides-Extra: dev-duckdb
Requires-Dist: duckdb; implementation_name != "pypy" and extra == "dev-duckdb"
Provides-Extra: dev-sqlite
Requires-Dist: aiosqlite; extra == "dev-sqlite"
Requires-Dist: apsw; implementation_name != "pypy" and extra == "dev-sqlite"
Provides-Extra: dev-postgres
Requires-Dist: pytest-postgresql; extra == "dev-postgres"
Requires-Dist: asyncpg; (python_version < "3.13" and implementation_name != "pypy") and extra == "dev-postgres"
Requires-Dist: psycopg>=3; extra == "dev-postgres"
Requires-Dist: psycopg2>=2.9.10; implementation_name != "pypy" and extra == "dev-postgres"
Requires-Dist: pygresql; extra == "dev-postgres"
Requires-Dist: pg8000; extra == "dev-postgres"
Provides-Extra: dev-mysql
Requires-Dist: pytest-mysql; extra == "dev-mysql"
Requires-Dist: mysqlclient; extra == "dev-mysql"
Requires-Dist: mysql-connector-python; extra == "dev-mysql"
Requires-Dist: pymysql; extra == "dev-mysql"
Provides-Extra: dev-mariadb
Requires-Dist: mariadb; extra == "dev-mariadb"
Provides-Extra: dev-mssql
Requires-Dist: pymssql; extra == "dev-mssql"
Provides-Extra: doc
Requires-Dist: sphinx; extra == "doc"
Requires-Dist: sphinx-rtd-theme; extra == "doc"
Requires-Dist: rstcheck; extra == "doc"
Provides-Extra: dist
Requires-Dist: build; extra == "dist"
Requires-Dist: wheel; extra == "dist"
Requires-Dist: twine; extra == "dist"
Dynamic: license-file
